{
  "generated_at": "2026-07-22T00:31:24Z",
  "source": "taostats dtao stake balances + SN25 delegation ledger. SN25 PnL marks alpha held at the live price vs TAO-weighted average purchase price.",
  "tao_usd": 201.42614961262032,
  "sn25_price_tao": 0.005841837,
  "sn25_price_usd": 1.1761294998390235,
  "wallets": [
    {
      "rank": 1,
      "coldkey": "5F6aRdsBHajN2NhZHBTB6ibBFu7YuZZEWruWzB8x6B6GiZ4D",
      "label": "SN25 owner",
      "hl": "green",
      "total_value_tao": 3715.645633992,
      "total_value_usd": 748428.1933799521,
      "n_positions": 1,
      "positions": [
        {
          "netuid": 25,
          "name": "Mainframe",
          "symbol": "\u05d0",
          "alpha": 636040.730002032,
          "value_tao": 3715.645633992,
          "value_usd": 748428.1933799521,
          "pct": 100.0,
          "is_sn25": true
        }
      ],
      "sn25": {
        "current_alpha": 636040.730002032,
        "current_value_tao": 3715.6462700328807,
        "current_value_usd": 748066.2656545372,
        "basis_available": false,
        "coverage": 0.15487557623889478,
        "book_alpha": 98507.174570472,
        "avg_buy_price_tao": 0.005517110564548588,
        "avg_buy_price_usd": 1.1672097135391861,
        "current_price_tao": 0.005841837,
        "current_price_usd": 1.1761294998390235,
        "cost_tao": 543.4749735065831,
        "cost_usd": 114978.53101195522,
        "pnl_tao": 0.0,
        "pnl_usd": 0.0,
        "pnl_pct": 0.0,
        "up": true,
        "n_buys": 65,
        "n_sells": 65,
        "alpha_bought": 872454.4367476251,
        "alpha_sold": 872556.346589889,
        "first_trade": "2025-02-23",
        "last_trade": "2026-07-21"
      },
      "major_buys": [
        {
          "date": "2026-01-02",
          "alpha": 98507.174570472,
          "tao": 392.755223978,
          "usd": 94958.07,
          "price_usd": 0.96,
          "is_transfer": false
        },
        {
          "date": "2026-07-21",
          "alpha": 81845.538342198,
          "tao": 458.326547098,
          "usd": 91525.17,
          "price_usd": 1.12,
          "is_transfer": false
        },
        {
          "date": "2026-05-19",
          "alpha": 70891.376950122,
          "tao": 366.651408895,
          "usd": 96095.58,
          "price_usd": 1.36,
          "is_transfer": false
        },
        {
          "date": "2026-02-17",
          "alpha": 59650.122859956,
          "tao": 287.874920983,
          "usd": 55362.9,
          "price_usd": 0.93,
          "is_transfer": false
        },
        {
          "date": "2026-03-25",
          "alpha": 46524.496696872,
          "tao": 242.742267059,
          "usd": 87870.1,
          "price_usd": 1.89,
          "is_transfer": false
        }
      ]
    },
    {
      "rank": 2,
      "coldkey": "5FFMceCxJufR8rKeLP8s8A2YcyENrcwaQMb47A7M4oKDhbXL",
      "label": "Keith",
      "hl": "purple",
      "total_value_tao": 1996.1696494139999,
      "total_value_usd": 402080.7664550362,
      "n_positions": 2,
      "positions": [
        {
          "netuid": 25,
          "name": "Mainframe",
          "symbol": "\u05d0",
          "alpha": 341700.711995674,
          "value_tao": 1996.159520562,
          "value_usd": 402078.72623937787,
          "pct": 99.9994925856125,
          "is_sn25": true
        },
        {
          "netuid": 0,
          "name": "Root",
          "symbol": "\u03a4",
          "alpha": 0.010128852,
          "value_tao": 0.010128852,
          "value_usd": 2.0402156583560886,
          "pct": 0.0005074143874982495,
          "is_sn25": false
        }
      ],
      "sn25": {
        "current_alpha": 341700.711995674,
        "current_value_tao": 1996.1598622626723,
        "current_value_usd": 401884.2874941103,
        "basis_available": true,
        "coverage": 0.7993690229773655,
        "book_alpha": 273144.9642986521,
        "avg_buy_price_tao": 0.00543172747672845,
        "avg_buy_price_usd": 1.2853326104746812,
        "current_price_tao": 0.005841837,
        "current_price_usd": 1.1761294998390235,
        "cost_tao": 1483.649007711,
        "cost_usd": 351082.13000000006,
        "pnl_tao": 512.5108545516723,
        "pnl_usd": 50802.15749411023,
        "pnl_pct": 34.54394212431572,
        "up": true,
        "n_buys": 4,
        "n_sells": 1,
        "alpha_bought": 506730.78689236206,
        "alpha_sold": 265263.430795286,
        "first_trade": "2025-10-23",
        "last_trade": "2026-07-01"
      },
      "major_buys": [
        {
          "date": "2026-01-24",
          "alpha": 265263.430795286,
          "tao": 1454.288527333,
          "usd": 345294.09,
          "price_usd": 1.3,
          "is_transfer": false
        },
        {
          "date": "2025-10-23",
          "alpha": 233585.82259371,
          "tao": 789.98,
          "usd": 305134.53,
          "price_usd": 1.31,
          "is_transfer": false
        },
        {
          "date": "2026-07-01",
          "alpha": 3940.766751683,
          "tao": 14.680240189,
          "usd": 2894.02,
          "price_usd": 0.73,
          "is_transfer": true
        },
        {
          "date": "2026-07-01",
          "alpha": 3940.766751683,
          "tao": 14.680240189,
          "usd": 2894.02,
          "price_usd": 0.73,
          "is_transfer": true
        }
      ]
    },
    {
      "rank": 3,
      "coldkey": "5GuRLEMgsMQsKSXQ9CjvQGpDxiMuSCcdkyQNz4nuoHURiuaC",
      "label": null,
      "hl": null,
      "total_value_tao": 22919.200432223002,
      "total_value_usd": 4616526.295262583,
      "n_positions": 17,
      "positions": [
        {
          "netuid": 28,
          "name": "gm",
          "symbol": "\u05d3",
          "alpha": 308412.628822649,
          "value_tao": 4596.949139414,
          "value_usd": 925945.7651172105,
          "pct": 20.05719681630328,
          "is_sn25": false
        },
        {
          "netuid": 62,
          "name": "Ridges",
          "symbol": "\u0632",
          "alpha": 278124.28170474,
          "value_tao": 3430.731433401,
          "value_usd": 691039.0229849492,
          "pct": 14.968809420496187,
          "is_sn25": false
        },
        {
          "netuid": 7,
          "name": "Allways",
          "symbol": "\u03b7",
          "alpha": 518182.262385714,
          "value_tao": 2075.9029159,
          "value_usd": 418141.13131934823,
          "pct": 9.057484016682391,
          "is_sn25": false
        },
        {
          "netuid": 24,
          "name": "Quasar",
          "symbol": "\u03c9",
          "alpha": 239270.346677373,
          "value_tao": 2059.232384609,
          "value_usd": 414783.2503894053,
          "pct": 8.984747922156327,
          "is_sn25": false
        },
        {
          "netuid": 74,
          "name": "Gittensor",
          "symbol": "\u0644",
          "alpha": 382791.520618926,
          "value_tao": 2047.510885098,
          "value_usd": 412422.23387521843,
          "pct": 8.93360521521215,
          "is_sn25": false
        }
      ],
      "sn25": {
        "current_alpha": 177685.065100695,
        "current_value_tao": 1038.0071876526488,
        "current_value_usd": 208980.64674574474,
        "basis_available": true,
        "coverage": 0.7999158554220045,
        "book_alpha": 142133.100845737,
        "avg_buy_price_tao": 0.004162252851192179,
        "avg_buy_price_usd": 1.2123663842244625,
        "current_price_tao": 0.005841837,
        "current_price_usd": 1.1761294998390235,
        "cost_tao": 591.5939042439544,
        "cost_usd": 172317.39355095706,
        "pnl_tao": 446.4132834086944,
        "pnl_usd": 36663.253194787685,
        "pnl_pct": 75.45941231074751,
        "up": true,
        "n_buys": 9,
        "n_sells": 7,
        "alpha_bought": 265547.11656318704,
        "alpha_sold": 125325.16267073399,
        "first_trade": "2025-03-03",
        "last_trade": "2026-06-30"
      },
      "major_buys": [
        {
          "date": "2025-10-09",
          "alpha": 124202.687884703,
          "tao": 399.798580911,
          "usd": 130407.67,
          "price_usd": 1.05,
          "is_transfer": false
        },
        {
          "date": "2026-05-03",
          "alpha": 34775.609164341,
          "tao": 161.69081059,
          "usd": 46901.32,
          "price_usd": 1.35,
          "is_transfer": true
        },
        {
          "date": "2026-05-03",
          "alpha": 34775.609164341,
          "tao": 161.69081059,
          "usd": 46901.32,
          "price_usd": 1.35,
          "is_transfer": true
        },
        {
          "date": "2026-03-21",
          "alpha": 20250.795022409,
          "tao": 100.0,
          "usd": 27596.9,
          "price_usd": 1.36,
          "is_transfer": false
        },
        {
          "date": "2026-05-21",
          "alpha": 20152.263637477,
          "tao": 100.0,
          "usd": 28356.41,
          "price_usd": 1.41,
          "is_transfer": false
        }
      ]
    },
    {
      "rank": 4,
      "coldkey": "5F9LSSxrEjTmnWtUNAj4tCHBQTwVgc4EjDFoSe9BeD3fN9Yi",
      "label": "Keith",
      "hl": "purple",
      "total_value_tao": 6802.854592618999,
      "total_value_usd": 1370272.8069657758,
      "n_positions": 15,
      "positions": [
        {
          "netuid": 64,
          "name": "Chutes",
          "symbol": "\u0634",
          "alpha": 23645.113782735,
          "value_tao": 1914.173563766,
          "value_usd": 385564.61063965294,
          "pct": 28.137799179815648,
          "is_sn25": false
        },
        {
          "netuid": 95,
          "name": "Actual",
          "symbol": "\u1685",
          "alpha": 21723.402779945,
          "value_tao": 1045.971308004,
          "value_usd": 210685.9731765219,
          "pct": 15.375476482164768,
          "is_sn25": false
        },
        {
          "netuid": 9,
          "name": "iota",
          "symbol": "\u03b9",
          "alpha": 25457.925739951,
          "value_tao": 881.034172186,
          "value_usd": 177463.32098056833,
          "pct": 12.95094816728715,
          "is_sn25": false
        },
        {
          "netuid": 13,
          "name": "Data Universe",
          "symbol": "\u03bd",
          "alpha": 126584.082275596,
          "value_tao": 870.318098039,
          "value_usd": 175304.8234261748,
          "pct": 12.793424968737135,
          "is_sn25": false
        },
        {
          "netuid": 25,
          "name": "Mainframe",
          "symbol": "\u05d0",
          "alpha": 101633.843474704,
          "value_tao": 593.728143995,
          "value_usd": 119592.37396156025,
          "pct": 8.727632435936329,
          "is_sn25": true
        }
      ],
      "sn25": {
        "current_alpha": 101633.843474704,
        "current_value_tao": 593.7283472627344,
        "current_value_usd": 119534.56149262121,
        "basis_available": true,
        "coverage": 1.0232245721498419,
        "book_alpha": 103994.246005348,
        "avg_buy_price_tao": 0.00391418868662467,
        "avg_buy_price_usd": 0.8198184691243622,
        "current_price_tao": 0.005841837,
        "current_price_usd": 1.1761294998390235,
        "cost_tao": 407.0531011881959,
        "cost_usd": 85256.40355784672,
        "pnl_tao": 186.67524607453845,
        "pnl_usd": 34278.1579347745,
        "pnl_pct": 45.86017046169892,
        "up": true,
        "n_buys": 586,
        "n_sells": 2,
        "alpha_bought": 111036.43601786302,
        "alpha_sold": 7042.1900125150005,
        "first_trade": "2026-04-19",
        "last_trade": "2026-07-06"
      },
      "major_buys": [
        {
          "date": "2026-07-06",
          "alpha": 93882.11608683,
          "tao": 362.0,
          "usd": 75090.3,
          "price_usd": 0.8,
          "is_transfer": false
        },
        {
          "date": "2026-04-24",
          "alpha": 5129.226614685,
          "tao": 25.0,
          "usd": 6198.36,
          "price_usd": 1.21,
          "is_transfer": false
        },
        {
          "date": "2026-06-05",
          "alpha": 5000.0,
          "tao": 20.001319935,
          "usd": 3977.32,
          "price_usd": 0.8,
          "is_transfer": true
        },
        {
          "date": "2026-04-24",
          "alpha": 2951.521044632,
          "tao": 14.5,
          "usd": 3581.29,
          "price_usd": 1.21,
          "is_transfer": false
        },
        {
          "date": "2026-04-24",
          "alpha": 2042.190012515,
          "tao": 9.992367271,
          "usd": 2477.45,
          "price_usd": 1.21,
          "is_transfer": false
        }
      ]
    },
    {
      "rank": 5,
      "coldkey": "5CqugXQG8zDdrLtYtyMyJEVWHrUb9RjQgXRHNeUihcNQNvMK",
      "label": null,
      "hl": null,
      "total_value_tao": 440.553107517,
      "total_value_usd": 88738.91614702405,
      "n_positions": 1,
      "positions": [
        {
          "netuid": 25,
          "name": "Mainframe",
          "symbol": "\u05d0",
          "alpha": 75413.505917841,
          "value_tao": 440.553107517,
          "value_usd": 88738.91614702405,
          "pct": 100.0,
          "is_sn25": true
        }
      ],
      "sn25": {
        "current_alpha": 75413.505917841,
        "current_value_tao": 440.55340917056253,
        "current_value_usd": 88696.04899625758,
        "basis_available": true,
        "coverage": 0.9952851165942296,
        "book_alpha": 75057.940030218,
        "avg_buy_price_tao": 0.004961793275648308,
        "avg_buy_price_usd": 0.9908783217263049,
        "current_price_tao": 0.005841837,
        "current_price_usd": 1.1761294998390235,
        "cost_tao": 372.4219821259496,
        "cost_usd": 74373.28564937605,
        "pnl_tao": 68.1314270446129,
        "pnl_usd": 14322.763346881533,
        "pnl_pct": 18.294147583794206,
        "up": true,
        "n_buys": 8,
        "n_sells": 3,
        "alpha_bought": 95711.52034944599,
        "alpha_sold": 20736.55490988,
        "first_trade": "2026-04-19",
        "last_trade": "2026-07-21"
      },
      "major_buys": [
        {
          "date": "2026-07-14",
          "alpha": 18483.618042713,
          "tao": 79.0,
          "usd": 15694.92,
          "price_usd": 0.85,
          "is_transfer": false
        },
        {
          "date": "2026-07-14",
          "alpha": 14635.813260892,
          "tao": 63.4,
          "usd": 12595.67,
          "price_usd": 0.86,
          "is_transfer": false
        },
        {
          "date": "2026-07-21",
          "alpha": 13048.470233088,
          "tao": 69.8,
          "usd": 14020.6,
          "price_usd": 1.07,
          "is_transfer": false
        },
        {
          "date": "2026-07-21",
          "alpha": 11083.605269424,
          "tao": 59.6,
          "usd": 11966.61,
          "price_usd": 1.08,
          "is_transfer": false
        },
        {
          "date": "2026-07-21",
          "alpha": 10585.572258701,
          "tao": 59.6,
          "usd": 11901.78,
          "price_usd": 1.12,
          "is_transfer": false
        }
      ]
    }
  ]
}